[
  {
    "rateplanId": 2858695,
    "rateCode": "DEMO1",
    "rateName": "demo locked rate",
    "rateCategory": "RACK",
    "pmsRateCode": null,
    "status": "active",
    "isAccessCodeRequired": false,
    "rateType": null,
    "ownerType": "system",
    "ownerName": "SYSTEM",
    "distributionOptions": {
      "isWebEnabled": true,
      "isOddEnabled": false,
      "isCallCenterEnabled": true,
      "isDirectConnectEnabled": false,
      "isMobileEnabled": false,
      "isGdsEnabled": true
    },
    "creationDateTime": "2018-11-28T00:00:00",
    "creationBy": "ihtejas",
    "lastUpdateDateTime": "2018-11-30T00:00:00",
    "lastUpdateBy": "ihtejas",
    "rateCategoryId": 1
  },
  {
    "rateplanId": 2859495,
    "rateCode": "TRANS1",
    "rateName": "check locked translation 123",
    "rateCategory": "RACK",
    "pmsRateCode": null,
    "status": "active",
    "isAccessCodeRequired": false,
    "rateType": null,
    "ownerType": "system",
    "ownerName": "SYSTEM",
    "distributionOptions": {
      "isWebEnabled": true,
      "isOddEnabled": false,
      "isCallCenterEnabled": true,
      "isDirectConnectEnabled": false,
      "isMobileEnabled": false,
      "isGdsEnabled": true
    },
    "creationDateTime": "2018-11-29T00:00:00",
    "creationBy": "ihtejas",
    "lastUpdateDateTime": "2018-11-29T00:00:00",
    "lastUpdateBy": "ihtejas",
    "rateCategoryId": 1
  },
  {
    "rateplanId": 2859396,
    "rateCode": "VIEW",
    "rateName": "view",
    "rateCategory": "CONSORTIA",
    "pmsRateCode": null,
    "status": "active",
    "isAccessCodeRequired": false,
    "rateType": null,
    "ownerType": "system",
    "ownerName": "SYSTEM",
    "distributionOptions": {
      "isWebEnabled": false,
      "isOddEnabled": false,
      "isCallCenterEnabled": false,
      "isDirectConnectEnabled": false,
      "isMobileEnabled": false,
      "isGdsEnabled": false
    },
    "creationDateTime": "2018-11-29T00:00:00",
    "creationBy": "iHakimSys",
    "lastUpdateDateTime": "2018-11-29T00:00:00",
    "lastUpdateBy": "iHakimSys",
    "rateCategoryId": 13
  },
  {
    "rateplanId": 2857497,
    "rateCode": "TEST",
    "rateName": "Test Rateplan Name",
    "rateCategory": "RACK",
    "pmsRateCode": null,
    "status": "active",
    "isAccessCodeRequired": false,
    "rateType": null,
    "ownerType": "system",
    "ownerName": "SYSTEM",
    "distributionOptions": {
      "isWebEnabled": false,
      "isOddEnabled": false,
      "isCallCenterEnabled": false,
      "isDirectConnectEnabled": false,
      "isMobileEnabled": false,
      "isGdsEnabled": false
    },
    "creationDateTime": "2018-11-28T00:00:00",
    "creationBy": "ihmmane",
    "lastUpdateDateTime": "2018-11-28T00:00:00",
    "lastUpdateBy": "ihmmane",
    "rateCategoryId": 1
  },
  {
    "rateplanId": 2856696,
    "rateCode": "GTYH",
    "rateName": "check locked delete 12345",
    "rateCategory": "RACK",
    "pmsRateCode": null,
    "status": "active",
    "isAccessCodeRequired": false,
    "rateType": null,
    "ownerType": "system",
    "ownerName": "SYSTEM",
    "distributionOptions": {
      "isWebEnabled": true,
      "isOddEnabled": false,
      "isCallCenterEnabled": false,
      "isDirectConnectEnabled": false,
      "isMobileEnabled": false,
      "isGdsEnabled": true
    },
    "creationDateTime": "2018-11-27T00:00:00",
    "creationBy": "ihtejas",
    "lastUpdateDateTime": "2018-11-28T00:00:00",
    "lastUpdateBy": "ihtejas",
    "rateCategoryId": 1
  },
  {
    "rateplanId": 1238999,
    "rateCode": "BCP",
    "rateName": "BCD Preferred Rate",
    "rateCategory": "CONSORTIA",
    "pmsRateCode": null,
    "status": "active",
    "isAccessCodeRequired": false,
    "rateType": null,
    "ownerType": "system",
    "ownerName": "SYSTEM",
    "distributionOptions": {
      "isWebEnabled": false,
      "isOddEnabled": false,
      "isCallCenterEnabled": false,
      "isDirectConnectEnabled": false,
      "isMobileEnabled": false,
      "isGdsEnabled": true
    },
    "creationDateTime": "2012-10-22T00:00:00",
    "creationBy": "ihndunn",
    "lastUpdateDateTime": "2018-11-27T00:00:00",
    "lastUpdateBy": "ihndunn",
    "rateCategoryId": 13
  },
  {
    "rateplanId": 480579,
    "rateCode": "BCD",
    "rateName": "BCD Standard Rate",
    "rateCategory": "CONSORTIA",
    "pmsRateCode": null,
    "status": "active",
    "isAccessCodeRequired": false,
    "rateType": null,
    "ownerType": "system",
    "ownerName": "SYSTEM",
    "distributionOptions": {
      "isWebEnabled": false,
      "isOddEnabled": false,
      "isCallCenterEnabled": false,
      "isDirectConnectEnabled": false,
      "isMobileEnabled": false,
      "isGdsEnabled": true
    },
    "creationDateTime": "2009-02-21T00:00:00",
    "creationBy": null,
    "lastUpdateDateTime": "2018-11-27T00:00:00",
    "lastUpdateBy": null,
    "rateCategoryId": 13
  },
  {
    "rateplanId": 2855495,
    "rateCode": "MM44",
    "rateName": "Test Rateplan Name MMT44",
    "rateCategory": "CONSORTIA",
    "pmsRateCode": null,
    "status": "active",
    "isAccessCodeRequired": false,
    "rateType": null,
    "ownerType": "system",
    "ownerName": "SYSTEM",
    "distributionOptions": {
      "isWebEnabled": true,
      "isOddEnabled": false,
      "isCallCenterEnabled": true,
      "isDirectConnectEnabled": true,
      "isMobileEnabled": false,
      "isGdsEnabled": false
    },
    "creationDateTime": "2018-11-27T00:00:00",
    "creationBy": "ihajain",
    "lastUpdateDateTime": "2018-11-27T00:00:00",
    "lastUpdateBy": "ihajain",
    "rateCategoryId": 13
  },
  {
    "rateplanId": 2856595,
    "rateCode": "MM44",
    "rateName": "Test Rateplan Name MMT44",
    "rateCategory": "CONSORTIA",
    "pmsRateCode": null,
    "status": "active",
    "isAccessCodeRequired": false,
    "rateType": null,
    "ownerType": "system",
    "ownerName": "SYSTEM",
    "distributionOptions": {
      "isWebEnabled": true,
      "isOddEnabled": false,
      "isCallCenterEnabled": true,
      "isDirectConnectEnabled": true,
      "isMobileEnabled": false,
      "isGdsEnabled": false
    },
    "creationDateTime": "2018-11-27T00:00:00",
    "creationBy": "ihajain",
    "lastUpdateDateTime": "2018-11-27T00:00:00",
    "lastUpdateBy": "ihajain",
    "rateCategoryId": 13
  },
  {
    "rateplanId": 2856596,
    "rateCode": "MM45",
    "rateName": "Test Rateplan Name MMT45",
    "rateCategory": "CONSORTIA",
    "pmsRateCode": null,
    "status": "active",
    "isAccessCodeRequired": false,
    "rateType": null,
    "ownerType": "system",
    "ownerName": "SYSTEM",
    "distributionOptions": {
      "isWebEnabled": true,
      "isOddEnabled": true,
      "isCallCenterEnabled": true,
      "isDirectConnectEnabled": true,
      "isMobileEnabled": false,
      "isGdsEnabled": false
    },
    "creationDateTime": "2018-11-27T00:00:00",
    "creationBy": "ihajain",
    "lastUpdateDateTime": "2018-11-27T00:00:00",
    "lastUpdateBy": "ihajain",
    "rateCategoryId": 13
  },
  {
    "rateplanId": 2855496,
    "rateCode": "MM45",
    "rateName": "Test Rateplan Name MMT45",
    "rateCategory": "CONSORTIA",
    "pmsRateCode": null,
    "status": "active",
    "isAccessCodeRequired": false,
    "rateType": null,
    "ownerType": "system",
    "ownerName": "SYSTEM",
    "distributionOptions": {
      "isWebEnabled": true,
      "isOddEnabled": true,
      "isCallCenterEnabled": true,
      "isDirectConnectEnabled": true,
      "isMobileEnabled": false,
      "isGdsEnabled": false
    },
    "creationDateTime": "2018-11-27T00:00:00",
    "creationBy": "ihajain",
    "lastUpdateDateTime": "2018-11-27T00:00:00",
    "lastUpdateBy": "ihajain",
    "rateCategoryId": 13
  },
  {
    "rateplanId": 1170220,
    "rateCode": "IH25",
    "rateName": "iHOTELIER OTA Sync 25",
    "rateCategory": "CHANNEL MANAGEMENT",
    "pmsRateCode": null,
    "status": "active",
    "isAccessCodeRequired": false,
    "rateType": null,
    "ownerType": "system",
    "ownerName": "SYSTEM",
    "distributionOptions": {
      "isWebEnabled": false,
      "isOddEnabled": false,
      "isCallCenterEnabled": true,
      "isDirectConnectEnabled": true,
      "isMobileEnabled": false,
      "isGdsEnabled": true
    },
    "creationDateTime": "2012-04-23T00:00:00",
    "creationBy": "ihxevi",
    "lastUpdateDateTime": "2018-11-27T00:00:00",
    "lastUpdateBy": "ihxevi",
    "rateCategoryId": 22
  },
  {
    "rateplanId": 2856400,
    "rateCode": "QWER1",
    "rateName": "qwer1",
    "rateCategory": "CONSORTIA",
    "pmsRateCode": null,
    "status": "active",
    "isAccessCodeRequired": false,
    "rateType": null,
    "ownerType": "system",
    "ownerName": "SYSTEM",
    "distributionOptions": {
      "isWebEnabled": true,
      "isOddEnabled": false,
      "isCallCenterEnabled": false,
      "isDirectConnectEnabled": false,
      "isMobileEnabled": false,
      "isGdsEnabled": false
    },
    "creationDateTime": "2018-11-27T00:00:00",
    "creationBy": "iHakimSys",
    "lastUpdateDateTime": "2018-11-27T00:00:00",
    "lastUpdateBy": "iHakimSys",
    "rateCategoryId": 13
  },
  {
    "rateplanId": 2856398,
    "rateCode": "QWERT1",
    "rateName": "qwerty1",
    "rateCategory": "CONSORTIA",
    "pmsRateCode": null,
    "status": "active",
    "isAccessCodeRequired": false,
    "rateType": null,
    "ownerType": "system",
    "ownerName": "SYSTEM",
    "distributionOptions": {
      "isWebEnabled": true,
      "isOddEnabled": false,
      "isCallCenterEnabled": false,
      "isDirectConnectEnabled": false,
      "isMobileEnabled": false,
      "isGdsEnabled": false
    },
    "creationDateTime": "2018-11-27T00:00:00",
    "creationBy": "iHakimSys",
    "lastUpdateDateTime": "2018-11-27T00:00:00",
    "lastUpdateBy": "iHakimSys",
    "rateCategoryId": 13
  },
  {
    "rateplanId": 480569,
    "rateCode": "ABC",
    "rateName": "ABC Global Services",
    "rateCategory": "CONSORTIA",
    "pmsRateCode": null,
    "status": "active",
    "isAccessCodeRequired": false,
    "rateType": null,
    "ownerType": "system",
    "ownerName": "SYSTEM",
    "distributionOptions": {
      "isWebEnabled": false,
      "isOddEnabled": false,
      "isCallCenterEnabled": false,
      "isDirectConnectEnabled": false,
      "isMobileEnabled": false,
      "isGdsEnabled": true
    },
    "creationDateTime": "2009-02-21T00:00:00",
    "creationBy": null,
    "lastUpdateDateTime": "2018-11-26T00:00:00",
    "lastUpdateBy": null,
    "rateCategoryId": 13
  },
  {
    "rateplanId": 480574,
    "rateCode": "ABCN",
    "rateName": "ABC Global Services Net",
    "rateCategory": "CONSORTIA",
    "pmsRateCode": null,
    "status": "active",
    "isAccessCodeRequired": false,
    "rateType": null,
    "ownerType": "system",
    "ownerName": "SYSTEM",
    "distributionOptions": {
      "isWebEnabled": false,
      "isOddEnabled": false,
      "isCallCenterEnabled": false,
      "isDirectConnectEnabled": false,
      "isMobileEnabled": false,
      "isGdsEnabled": true
    },
    "creationDateTime": "2009-02-21T00:00:00",
    "creationBy": null,
    "lastUpdateDateTime": "2018-11-26T00:00:00",
    "lastUpdateBy": null,
    "rateCategoryId": 13
  },
  {
    "rateplanId": 2853997,
    "rateCode": "LOCSYS",
    "rateName": "System LOck Check Rate",
    "rateCategory": "OTA MERCHANT",
    "pmsRateCode": null,
    "status": "active",
    "isAccessCodeRequired": false,
    "rateType": null,
    "ownerType": "system",
    "ownerName": "SYSTEM",
    "distributionOptions": {
      "isWebEnabled": true,
      "isOddEnabled": true,
      "isCallCenterEnabled": true,
      "isDirectConnectEnabled": true,
      "isMobileEnabled": false,
      "isGdsEnabled": false
    },
    "creationDateTime": "2018-11-26T00:00:00",
    "creationBy": "ihanuja",
    "lastUpdateDateTime": "2018-11-26T00:00:00",
    "lastUpdateBy": "ihanuja",
    "rateCategoryId": 21
  },
  {
    "rateplanId": 1170204,
    "rateCode": "IH12",
    "rateName": "iHOTELIER OTA Sync 12",
    "rateCategory": "CHANNEL MANAGEMENT",
    "pmsRateCode": null,
    "status": "active",
    "isAccessCodeRequired": false,
    "rateType": null,
    "ownerType": "system",
    "ownerName": "SYSTEM",
    "distributionOptions": {
      "isWebEnabled": true,
      "isOddEnabled": false,
      "isCallCenterEnabled": false,
      "isDirectConnectEnabled": true,
      "isMobileEnabled": false,
      "isGdsEnabled": false
    },
    "creationDateTime": "2012-04-23T00:00:00",
    "creationBy": "ihxevi",
    "lastUpdateDateTime": "2018-11-26T00:00:00",
    "lastUpdateBy": "ihxevi",
    "rateCategoryId": 22
  },
  {
    "rateplanId": 1170208,
    "rateCode": "IH15",
    "rateName": "iHOTELIER OTA Sync 15",
    "rateCategory": "CHANNEL MANAGEMENT",
    "pmsRateCode": null,
    "status": "active",
    "isAccessCodeRequired": false,
    "rateType": null,
    "ownerType": "system",
    "ownerName": "SYSTEM",
    "distributionOptions": {
      "isWebEnabled": true,
      "isOddEnabled": false,
      "isCallCenterEnabled": false,
      "isDirectConnectEnabled": true,
      "isMobileEnabled": false,
      "isGdsEnabled": false
    },
    "creationDateTime": "2012-04-23T00:00:00",
    "creationBy": "ihxevi",
    "lastUpdateDateTime": "2018-11-26T00:00:00",
    "lastUpdateBy": "ihxevi",
    "rateCategoryId": 22
  },
  {
    "rateplanId": 2844497,
    "rateCode": "SYS56",
    "rateName": "test system rate 1",
    "rateCategory": "RACK",
    "pmsRateCode": null,
    "status": "active",
    "isAccessCodeRequired": false,
    "rateType": null,
    "ownerType": "system",
    "ownerName": "SYSTEM",
    "distributionOptions": {
      "isWebEnabled": true,
      "isOddEnabled": false,
      "isCallCenterEnabled": true,
      "isDirectConnectEnabled": false,
      "isMobileEnabled": false,
      "isGdsEnabled": true
    },
    "creationDateTime": "2018-11-19T00:00:00",
    "creationBy": "ihtejas",
    "lastUpdateDateTime": "2018-11-26T00:00:00",
    "lastUpdateBy": "ihtejas",
    "rateCategoryId": 1
  },
  {
    "rateplanId": 480697,
    "rateCode": "CT1",
    "rateName": "Priceline Tier 2",
    "rateCategory": "OTA MERCHANT",
    "pmsRateCode": null,
    "status": "active",
    "isAccessCodeRequired": false,
    "rateType": null,
    "ownerType": "system",
    "ownerName": "SYSTEM",
    "distributionOptions": {
      "isWebEnabled": true,
      "isOddEnabled": false,
      "isCallCenterEnabled": false,
      "isDirectConnectEnabled": false,
      "isMobileEnabled": false,
      "isGdsEnabled": true
    },
    "creationDateTime": "2009-02-21T00:00:00",
    "creationBy": null,
    "lastUpdateDateTime": "2018-11-23T00:00:00",
    "lastUpdateBy": null,
    "rateCategoryId": 21
  },
  {
    "rateplanId": 1170202,
    "rateCode": "IH10",
    "rateName": "iHOTELIER OTA Sync 10",
    "rateCategory": "CHANNEL MANAGEMENT",
    "pmsRateCode": null,
    "status": "active",
    "isAccessCodeRequired": false,
    "rateType": null,
    "ownerType": "system",
    "ownerName": "SYSTEM",
    "distributionOptions": {
      "isWebEnabled": false,
      "isOddEnabled": false,
      "isCallCenterEnabled": false,
      "isDirectConnectEnabled": true,
      "isMobileEnabled": false,
      "isGdsEnabled": false
    },
    "creationDateTime": "2012-04-23T00:00:00",
    "creationBy": "ihxevi",
    "lastUpdateDateTime": "2018-11-23T00:00:00",
    "lastUpdateBy": "ihxevi",
    "rateCategoryId": 22
  },
  {
    "rateplanId": 2852795,
    "rateCode": "CON34",
    "rateName": "new consortia locked rate",
    "rateCategory": "CONSORTIA",
    "pmsRateCode": null,
    "status": "active",
    "isAccessCodeRequired": false,
    "rateType": null,
    "ownerType": "system",
    "ownerName": "SYSTEM",
    "distributionOptions": {
      "isWebEnabled": true,
      "isOddEnabled": false,
      "isCallCenterEnabled": false,
      "isDirectConnectEnabled": false,
      "isMobileEnabled": false,
      "isGdsEnabled": true
    },
    "creationDateTime": "2018-11-23T00:00:00",
    "creationBy": "ihtejas",
    "lastUpdateDateTime": "2018-11-23T00:00:00",
    "lastUpdateBy": "ihtejas",
    "rateCategoryId": 13
  },
  {
    "rateplanId": 2853195,
    "rateCode": "GHTY",
    "rateName": "not E and locked",
    "rateCategory": "RACK",
    "pmsRateCode": null,
    "status": "active",
    "isAccessCodeRequired": false,
    "rateType": null,
    "ownerType": "system",
    "ownerName": "SYSTEM",
    "distributionOptions": {
      "isWebEnabled": true,
      "isOddEnabled": false,
      "isCallCenterEnabled": false,
      "isDirectConnectEnabled": false,
      "isMobileEnabled": false,
      "isGdsEnabled": false
    },
    "creationDateTime": "2018-11-23T00:00:00",
    "creationBy": "ihtejas",
    "lastUpdateDateTime": "2018-11-23T00:00:00",
    "lastUpdateBy": "ihtejas",
    "rateCategoryId": 1
  },
  {
    "rateplanId": 2844496,
    "rateCode": "SYS145",
    "rateName": "test system rate",
    "rateCategory": "RACK",
    "pmsRateCode": null,
    "status": "active",
    "isAccessCodeRequired": false,
    "rateType": null,
    "ownerType": "system",
    "ownerName": "SYSTEM",
    "distributionOptions": {
      "isWebEnabled": true,
      "isOddEnabled": false,
      "isCallCenterEnabled": true,
      "isDirectConnectEnabled": false,
      "isMobileEnabled": false,
      "isGdsEnabled": true
    },
    "creationDateTime": "2018-11-19T00:00:00",
    "creationBy": "ihtejas",
    "lastUpdateDateTime": "2018-11-23T00:00:00",
    "lastUpdateBy": "ihtejas",
    "rateCategoryId": 1
  },
  {
    "rateplanId": 2850896,
    "rateCode": "TYHGR",
    "rateName": "E and unlocked sys rate",
    "rateCategory": "RACK",
    "pmsRateCode": null,
    "status": "active",
    "isAccessCodeRequired": false,
    "rateType": null,
    "ownerType": "system",
    "ownerName": "SYSTEM",
    "distributionOptions": {
      "isWebEnabled": true,
      "isOddEnabled": false,
      "isCallCenterEnabled": false,
      "isDirectConnectEnabled": false,
      "isMobileEnabled": false,
      "isGdsEnabled": true
    },
    "creationDateTime": "2018-11-22T00:00:00",
    "creationBy": "ihtejas",
    "lastUpdateDateTime": "2018-11-22T00:00:00",
    "lastUpdateBy": "ihtejas",
    "rateCategoryId": 1
  }
]